{
  "openapi": "3.0.1",
  "info": {
    "title": "CutifyApi",
    "version": "1.0"
  },
  "paths": {
    "/api/Account/Register": {
      "post": {
        "tags": [
          "Account"
        ],
        "requestBody": {
          "content": {
            "application/json": {
              "schema": {
                "$ref": "#/components/schemas/RegisterDto"
              }
            },
            "text/json": {
              "schema": {
                "$ref": "#/components/schemas/RegisterDto"
              }
            },
            "application/*+json": {
              "schema": {
                "$ref": "#/components/schemas/RegisterDto"
              }
            }
          }
        },
        "responses": {
          "200": {
            "description": "OK"
          }
        }
      }
    },
    "/api/Account/VerifyEmail": {
      "post": {
        "tags": [
          "Account"
        ],
        "requestBody": {
          "content": {
            "application/json": {
              "schema": {
                "type": "array",
                "items": {
                  "type": "string"
                }
              }
            },
            "text/json": {
              "schema": {
                "type": "array",
                "items": {
                  "type": "string"
                }
              }
            },
            "application/*+json": {
              "schema": {
                "type": "array",
                "items": {
                  "type": "string"
                }
              }
            }
          }
        },
        "responses": {
          "200": {
            "description": "OK"
          }
        }
      }
    },
    "/api/Account/RefreshToken": {
      "post": {
        "tags": [
          "Account"
        ],
        "requestBody": {
          "content": {
            "application/json": {
              "schema": {
                "type": "string"
              }
            },
            "text/json": {
              "schema": {
                "type": "string"
              }
            },
            "application/*+json": {
              "schema": {
                "type": "string"
              }
            }
          }
        },
        "responses": {
          "200": {
            "description": "OK"
          }
        }
      }
    },
    "/api/Account/Login": {
      "post": {
        "tags": [
          "Account"
        ],
        "requestBody": {
          "content": {
            "application/json": {
              "schema": {
                "$ref": "#/components/schemas/LoginDto"
              }
            },
            "text/json": {
              "schema": {
                "$ref": "#/components/schemas/LoginDto"
              }
            },
            "application/*+json": {
              "schema": {
                "$ref": "#/components/schemas/LoginDto"
              }
            }
          }
        },
        "responses": {
          "200": {
            "description": "OK"
          }
        }
      }
    },
    "/api/Reservation/AddReservation": {
      "post": {
        "tags": [
          "Reservation"
        ],
        "requestBody": {
          "content": {
            "application/json": {
              "schema": {
                "$ref": "#/components/schemas/ReservationCreateDto"
              }
            },
            "text/json": {
              "schema": {
                "$ref": "#/components/schemas/ReservationCreateDto"
              }
            },
            "application/*+json": {
              "schema": {
                "$ref": "#/components/schemas/ReservationCreateDto"
              }
            }
          }
        },
        "responses": {
          "200": {
            "description": "OK"
          }
        }
      }
    },
    "/api/Reservation/MyReservations": {
      "get": {
        "tags": [
          "Reservation"
        ],
        "responses": {
          "200": {
            "description": "OK"
          }
        }
      }
    }
  },
  "components": {
    "schemas": {
      "LoginDto": {
        "required": [
          "email",
          "password"
        ],
        "type": "object",
        "properties": {
          "email": {
            "minLength": 1,
            "type": "string",
            "format": "email"
          },
          "password": {
            "minLength": 1,
            "type": "string",
            "format": "password"
          }
        },
        "additionalProperties": false
      },
      "RegisterDto": {
        "required": [
          "address",
          "email",
          "image",
          "lastName",
          "name",
          "password"
        ],
        "type": "object",
        "properties": {
          "image": {
            "minLength": 1,
            "type": "string"
          },
          "name": {
            "minLength": 1,
            "type": "string"
          },
          "lastName": {
            "minLength": 1,
            "type": "string"
          },
          "email": {
            "minLength": 1,
            "type": "string",
            "format": "email"
          },
          "address": {
            "minLength": 1,
            "type": "string"
          },
          "password": {
            "maxLength": 100,
            "minLength": 8,
            "type": "string",
            "format": "password"
          }
        },
        "additionalProperties": false
      },
      "ReservationCreateDto": {
        "required": [
          "barberFullName",
          "barberId",
          "fullName",
          "phoneNumber",
          "reservationTime"
        ],
        "type": "object",
        "properties": {
          "barberId": {
            "type": "integer",
            "format": "int32"
          },
          "barberFullName": {
            "minLength": 1,
            "type": "string"
          },
          "reservationTime": {
            "type": "string",
            "format": "date-time"
          },
          "fullName": {
            "minLength": 1,
            "type": "string"
          },
          "phoneNumber": {
            "minLength": 1,
            "type": "string"
          }
        },
        "additionalProperties": false
      }
    }
  }
}